npm_accel/__init__.py
npm_accel/cli.py
npm_accel/exceptions.py
npm_accel/tests.py
npm_accel-2.0.1.dist-info/LICENSE.txt
npm_accel-2.0.1.dist-info/METADATA
npm_accel-2.0.1.dist-info/WHEEL
npm_accel-2.0.1.dist-info/entry_points.txt
npm_accel-2.0.1.dist-info/top_level.txt
npm_accel-2.0.1.dist-info/RECORD
